migrationmaker/__init__.py
migrationmaker/migration.py
migrationmaker/version_ctl.py
sqlalchemy_migration_maker-0.4.dist-info/METADATA
sqlalchemy_migration_maker-0.4.dist-info/RECORD
sqlalchemy_migration_maker-0.4.dist-info/WHEEL
sqlalchemy_migration_maker-0.4.dist-info/top_level.txt
tests/__init__.py
tests/model.py
tests/test_meta.py
tests/test_version_control.py
