Metadata-Version: 2.1
Name: sqlalchemy-migration-maker
Version: 0.4
Summary: SQLAlachemy migration maker.Generate SQL command to auto migrate
Home-page: https://github.com/panmpan17/MigrationMaker
Author: Michael Pan
Author-email: panmpan@gmail.com
License: UNKNOWN
Keywords: sqlalchemy migration database db postgres python python3
Platform: UNKNOWN
Classifier: Programming Language :: Python :: 3
Classifier: Programming Language :: Python :: 3.6
Classifier: License :: OSI Approved :: MIT License
Classifier: Operating System :: OS Independent
Requires-Python: >=3.6
Requires-Dist: sqlalchemy
